stac_merkle_tree_cli/__init__.py
stac_merkle_tree_cli/cli.py
stac_merkle_tree_cli/compute_merkle_info.py
tests/__init__.py
tests/test_compute_merkle_info.py
stac_merkle_tree_cli-0.3.0.dist-info/LICENSE
stac_merkle_tree_cli-0.3.0.dist-info/METADATA
stac_merkle_tree_cli-0.3.0.dist-info/WHEEL
stac_merkle_tree_cli-0.3.0.dist-info/entry_points.txt
stac_merkle_tree_cli-0.3.0.dist-info/top_level.txt
stac_merkle_tree_cli-0.3.0.dist-info/RECORD
