Metadata-Version: 2.1
Name: stac-merkle-tree-cli
Version: 0.3.0
Summary: A CLI tool for computing and adding Merkle Tree information to STAC catalogs, collections, or items.
Home-page: https://github.com/stacchain/stac-merkle-tree-cli
Author: Jonathan Healy
Author-email: jonathan.d.healy@gmail.com
Classifier: Programming Language :: Python :: 3
Classifier: License :: OSI Approved :: Apache Software License
Classifier: Operating System :: OS Independent
Requires-Python: >=3.6
License-File: LICENSE
Requires-Dist: click>=8.0.0
